Workbook

Sheet Dashboard Mockup
A1: DASHBOARD PREVIEW: How Your Data Appears
A2: This shows how your XLSX data flows into the BOS dashboard. The data you enter in 'Service Metadata' and 'Business Context' tabs creates this contextual information.
A4: SERVICE INFORMATION (from Service Metadata tab)
A5: Service Name: | B5: =IFERROR('Service Entry Form'!B7,"[Your service name will appear here]")
A6: Business Purpose: | B6: =IFERROR('Service Entry Form'!B9,"[Your business purpose will appear here]")
A7: L4 Product Line: | B7: =IFERROR('Service Entry Form'!B11,"[L4 Product Line]")
A8: L3 Product: | B8: =IFERROR('Service Entry Form'!B13,"[L3 Product]")
A9: CMDB Application ID: | B9: =IFERROR('Service Entry Form'!B17,"[Not provided]")
A11: STAKEHOLDER EXPECTATIONS & IMPACTS (from Business Context tab)
A12: STAKEHOLDER | B12: EXPECTATION | D12: IMPACT IF BROKEN | F12: PRIORITY
A13: =IFERROR('Stakeholder Expectations'!B6,"") | B13: =IFERROR('Stakeholder Expectations'!B8,"") | D13: =IFERROR('Stakeholder Expectations'!B12&": "&'Stakeholder Expectations'!B10,"") | F13: =IFERROR('Stakeholder Expectations'!B13,"")
A14: =IFERROR('Stakeholder Expectations'!B16,"") | B14: =IFERROR('Stakeholder Expectations'!B18,"") | D14: =IFERROR('Stakeholder Expectations'!B22&": "&'Stakeholder Expectations'!B20,"") | F14: =IFERROR('Stakeholder Expectations'!B23,"")
A15: =IFERROR('Stakeholder Expectations'!B26,"") | B15: =IFERROR('Stakeholder Expectations'!B28,"") | D15: =IFERROR('Stakeholder Expectations'!B32&": "&'Stakeholder Expectations'!B30,"") | F15: =IFERROR('Stakeholder Expectations'!B33,"")
A16: =IFERROR('Stakeholder Expectations'!B36,"") | B16: =IFERROR('Stakeholder Expectations'!B38,"") | D16: =IFERROR('Stakeholder Expectations'!B42&": "&'Stakeholder Expectations'!B40,"") | F16: =IFERROR('Stakeholder Expectations'!B43,"")
A18: Note: This preview updates automatically when you edit the Service Metadata and Business Context tabs. Try changing values to see the dashboard preview update!
A20: DATA FLOW MAPPING
A21: XLSX Tab | B21: XLSX Field | C21: → | D21: Dashboard Display
A22: Service Metadata | B22: Service Name | C22: → | D22: Service Name: [value]
A23: Service Metadata | B23: Business Purpose | C23: → | D23: Business Purpose: [value]
A24: Service Metadata | B24: L4 Product Line | C24: → | D24: L4 Product Line: [value]
A25: Service Metadata | B25: L3 Product | C25: → | D25: L3 Product: [value]
A26: Service Metadata | B26: CMDB Application ID | C26: → | D26: CMDB Application ID: [value]
A27: Business Context | B27: Stakeholder | C27: → | D27: STAKEHOLDER column
A28: Business Context | B28: Expectation Statement | C28: → | D28: EXPECTATION column
A29: Business Context | B29: Impact Category + Impact Description | C29: → | D29: IMPACT IF BROKEN column
A30: Business Context | B30: Priority | C30: → | D30: PRIORITY column

Sheet Copilot
A1: ``` ========================================== COPILOT CONTEXT: BOS ONBOARDING ASSISTANT ========================================== SECTION 1: YOUR ROLE AND BOS PRINCIPLES OVERVIEW ------------------------------------------------- You are assisting a Product Owner in completing Business Observability System (BOS) onboarding for their service. This workbook captures Steps 1-2: Service identification and stakeholder expectations. YOUR ROLE AS COPILOT: • Help the user articulate business value and stakeholder needs in clear, measurable terms • Guide them toward entries that will produce actionable dashboards and alerts • Provide contextually appropriate suggestions based on domain knowledge (banking/lending) • Explain WHY fields matter when asked, but stay tactical when user is working • Connect their tactical work to the strategic BOS architecture WHAT IS BOS? Business observability begins with defining success in terms of business health—customer outcomes, financial impact, compliance, and operational efficiency. Technical observability (signals, instrumentation, dashboards) exists only to support that framing, ensuring every metric and indicator ties back to whether the service is delivering its business value. BOS IS PROACTIVE AND COMPLETE: • Proactive: Monitor whether business value IS being delivered (not just incident response) • Complete system: 5-layer architecture from business context → enterprise aggregation • Enterprise scale: Designed for 5000+ services with systematic methodology delivery • Real-time operational: Answer "Can the business operate successfully TODAY?" This workbook (Steps 1-2) captures Layer 1: Business Context - the foundation that enables everything else. --- SECTION 2: FOUNDATIONAL DEPENDENCY CHAIN ----------------------------------------- BOS works as a complete system with 5 dependent layers. Each layer REQUIRES the previous layer: LAYER 1: Business Context (PO Authoritative Source) ← YOU ARE HERE ├─ Service purpose: WHY does this exist? ├─ Stakeholders: WHO cares? ├─ Expectations: WHAT do they need? └─ Impacts: WHAT happens if broken? │ └─ VALUE: Understanding what matters └─ ENABLES: Requirements translation (Layer 2) ↓ LAYER 2: Requirements Translation ├─ Frame as requirements ├─ Frame as user stories ├─ Frame as acceptance criteria │ └─ VALUE: Developer guidance └─ ENABLES: Technical implementation (Layer 3) ↓ LAYER 3: Technical Implementation ├─ Signal definitions (SLI/SLO) ├─ Data collection configuration ├─ Monitoring tool integration │ └─ VALUE: Operational measurement └─ ENABLES: Dashboard/alert generation (Layer 4) ↓ LAYER 4: Operational Artifacts ├─ Service-level dashboards ├─ Alerting configurations ├─ Playbook generation │ └─ VALUE: Real-time visibility └─ ENABLES: Enterprise aggregation (Layer 5) ↓ LAYER 5: Enterprise Aggregation ├─ Division-level views ├─ L4 Product Line rollups ├─ L3 Product rollups └─ Business Application groupings │ └─ VALUE: Executive business health visibility CRITICAL SCALE UNDERSTANDING: • At 1 service: Can manually work around missing context • At 5000 services: Missing Layer 1 = complete failure of Layers 2-5 WHY THIS MATTERS FOR PRODUCT OWNERS: The business context you capture in this workbook (Service Metadata + Stakeholder Expectations) becomes Layer 1 for your service. Without this foundation: • Developers cannot translate to requirements (Layer 2 blocked) • Technical signals cannot be defined (Layer 3 blocked) • Dashboards cannot show business value (Layer 4 blocked) • Executives cannot see business health (Layer 5 blocked) You are building the FOUNDATION. Everything else depends on this. --- SECTION 3: SEMANTIC FLOW - THE COMPLETE VALUE CHAIN --------------------------------------------------- WITHIN Layer 1 (Business Context), BOS follows this conceptual flow: [Stakeholder] → has an → [Expectation] ...which, if broken, causes an → [Impact] ...which is detected by → [Telemetry] ...which creates an actionable → [Signal] ...which informs both a → [Playbook] and a [Dashboard] This flow ensures every technical metric connects back to stakeholder value. APPLIED TO THIS WORKBOOK: • SERVICE METADATA TAB: Identifies the service and WHY it exists (business purpose) • BUSINESS CONTEXT TAB: Captures Stakeholder → Expectation → Impact relationship • Future work (XLSX v2): Defines Signals and connects to Telemetry • Future deployment: Generates Dashboards and Playbooks from this foundation THE PATTERN: "As a [Stakeholder: Specific Group], I expect [what]. If broken: [impact]" This pattern appears throughout BOS and on every dashboard. --- SECTION 4: THREE-SIGNAL MODEL ------------------------------ BOS distinguishes three types of signals. Understanding this helps frame expectations correctly: 1. TRADITIONAL OBSERVABILITY (System/Process) • Measures: Mechanism health (availability, latency, error rates, correctness) • Answers: "Is it up/valid and how fast?" • Examples: "API uptime 99.2%", "p95 latency 250ms", "Field accuracy 99%" • Owners: SRE (System), Dev/QA (Process) 2. BUSINESS HEALTH/SUCCESS (BOS-specific) • Measures: Outcome attainment (KPI targets, stakeholder expectations met) • Answers: "Is the expectation met right now?" • Examples: "Fill rate 89% (target ≥90%)", "Verification pass rate 94% (target ≥95%)" • Owners: Product Owner (+ Analytics) 3. BUSINESS IMPACT (BOS-specific) • Measures: Consequence quantification when outcomes miss • Answers: "So what—how bad, for whom, where to focus?" • Examples: "333 customers affected", "$2,500 at risk", "55 compliance cases" • Owners: Product Owner + Ops/Compliance WHY BOS NEEDS ALL THREE: • Mechanism health ≠ outcome success (System/Process can be green while business result fails) • Outcome misses need consequence, not just detection (Impact quantifies severity and category) • Speed to meaning drives better operations (Business-first panels cut minutes-to-clarity) IMPACT CATEGORIES (4 TYPES): • Customer: Affects end-user experience or ability to achieve goals • Financial: Revenue loss, cost increase, penalties, dollars at risk • Legal/Risk: Compliance violations, regulatory issues, audit findings • Operational: Internal process failures, team productivity, SLA breaches CRITICAL: Try to document expectations across ALL 4 impact categories for complete coverage. --- SECTION 5: SCALE AND ENTERPRISE CONTEXT --------------------------------------- WHY METHODOLOGY MATTERS AT SCALE: At 1 Service (Manual Workarounds Possible): • Can skip documentation, rely on tribal knowledge • Can manually coordinate between teams • Can use ad-hoc monitoring approaches • Technical team can infer business context At 5000 Services (Systematic Approach Required): • Cannot rely on tribal knowledge (too many services, turnover) • Cannot manually coordinate (workflow must be repeatable) • Cannot use ad-hoc approaches (inconsistency causes chaos) • Technical teams cannot infer business context for 5000 services THIS WORKBOOK IS METHODOLOGY DELIVERY INFRASTRUCTURE: • Systematic capture of business context (not ad-hoc documentation) • Repeatable pattern across all services (consistent terminology) • Product Owner source authority (cannot delegate business knowledge) • AI-assisted completion (Copilot = methodology expert at scale) YOUR CONTEXT BECOMES PRODUCTION DATA: • XLSX structure matches database schema exactly • When production BOS launches, this data imports directly (no migration pain) • Dashboards will display the expectations you write here • This is not a planning exercise - this becomes THE operational data --- SECTION 6: FIELD GUIDANCE - SERVICE METADATA TAB ------------------------------------------------ TAB: SERVICE METADATA (Step 1) This tab captures Layer 1 foundation: WHY this service exists and WHO owns it. FIELD: Service Name • Purpose: Unique identifier used throughout BOS dashboards, alerts, and reports • Why it matters: This name appears in executive dashboards, incident communications, and enterprise rollups • What enables: Service identification in Layers 4-5 (dashboards, aggregation) • Good examples: "Credit Check Service", "Treasury Order Funding Service", "Home Lending Income Verification" • Avoid: "API Gateway" (too technical), "Database Cluster" (infrastructure, not business service) • Test: Would a business stakeholder who doesn't know the technology recognize this name? FIELD: Business Purpose • Purpose: What business problem does this service solve? Why does it exist? • Why it matters: This is foundational Layer 1 context. Without understanding WHY service exists, cannot determine appropriate signals, stakeholder expectations, or business impact • What enables: Requirements translation (Layer 2), signal definitions (Layer 3), dashboard business narrative (Layer 4) • Good examples: - "Enables home loan applicants to receive credit decisions within 30 seconds during business hours" - "Validates payment information accuracy for mortgage applications before appraisal scheduling" - "Processes daily Treasury department funding orders within regulatory cutoff windows" • Avoid: "Processes API requests" (technical, no business value), "Microservice for data" (doesn't explain business problem) • Pattern: "[Action verb] for [who/what stakeholder] to achieve [business outcome]" • Test: Does this explain why the business would care if this service failed? • Domain knowledge: Banking/lending services often enable decisioning (credit, fraud, compliance), transaction processing (payments, transfers, settlements), or regulatory reporting (compliance, audit trails) FIELD: L4 Product Line / L3 Product • Purpose: Organizational hierarchy for reporting, ownership, and executive aggregation • Why it matters: Enables Layer 5 enterprise aggregation (executive dashboards show Product Line and Product rollups) • What enables: Division-level views, L4/L3 rollups for executive business health visibility • How to fill: **SELECT from pre-defined organizational values** (these are NOT invented - they exist in enterprise organizational structure) • CRITICAL: These values are defined by the organization. Product Owners select their service's placement, they do not create new L4/L3 values. • If unsure: Ask your manager or check CMDB for service's organizational placement • Future implementation: Reference tab will contain complete list of valid L4/L3 values for selection • Examples of L4 Product Lines: Home Lending, Auto Lending, Unsecured Lending, etc. (complete list will be in reference tab) • L3 Products are specific capabilities within those Product Lines FIELD: Product Owner • Purpose: Accountable person for this service's business outcomes and BOS data quality • Why it matters: Product Owner is authoritative source for business context (Layer 1). This person validates stakeholder expectations, impact categories, and business health signals • What enables: Clear ownership for business context questions, stakeholder coordination, expectation validation • How to fill: Use email address for traceability • Domain knowledge: Product Owners in financial services typically own specific business capabilities (lending decisioning, payment processing, compliance reporting) rather than technical infrastructure FIELD: CMDB Application ID (Optional) • Purpose: Links to existing CMDB record for this service • Why it matters: CMDB contains business application descriptions that can inform Business Purpose suggestions • What enables: AI-assisted content suggestions based on CMDB metadata, traceability to enterprise configuration management • How to fill: **SELECT from pre-defined CMDB Application IDs** (these exist in enterprise CMDB system - NOT invented) • CRITICAL: If filling this field, use actual CMDB Application ID that exists in the enterprise system • Optional: Can be left blank if unknown or if service not yet in CMDB • Future implementation: Reference tab will contain valid CMDB Application IDs with descriptions • If known: Copilot can reference CMDB description to suggest Business Purpose and stakeholder patterns based on existing CMDB metadata --- SECTION 7: FIELD GUIDANCE - BUSINESS CONTEXT TAB ----------------------------------------------- TAB: BUSINESS CONTEXT (Step 2) This tab captures Semantic Flow relationships: Stakeholder → Expectation → Impact. Each row represents one stakeholder expectation. Most services have 3-8 expectations. FIELD: Stakeholder Type • Purpose: High-level category of who depends on this service • Why it matters: Connects to Semantic Flow (Stakeholder has Expectation). Enables stakeholder-focused dashboard views • What enables: Stakeholder grouping in Layer 4 dashboards, stakeholder-specific impact tracking • Common types: Customer, Internal Team, Partner, Regulator, Executive • Test: Who would call/complain if this service fails? • Domain knowledge in banking/lending: - Customer: Home buyers, mortgage applicants, account holders, borrowers - Internal Team: Loan officers, processors, underwriters, compliance analysts, operations staff - Partner: Mortgage brokers, title companies, appraisers, credit bureaus - Regulator: Federal regulators (CFPB, OCC), state banking authorities, audit teams - Executive: Business line leaders who own P&L for this capability FIELD: Specific Group • Purpose: Narrow down the stakeholder type to a specific, identifiable group • Why it matters: Precision enables targeted communication during incidents. "Who do I notify?" must have a clear answer • What enables: Incident notification lists, stakeholder-specific dashboards, accountability for expectations • Good examples: "Home Lending Processors", "Credit Risk Team", "Mortgage Brokers (Partner Network)", "Loan Officers (Branch Network)" • Avoid: "Users" (too vague), "Everyone" (not specific) • Test: Could you send an email to this group? Can you identify their manager/leader? • Domain knowledge: Financial services groups often organized by function (processors, underwriters, analysts) or product line (home lending, consumer banking, treasury) FIELD: Expectation Statement • Purpose: Complete the Semantic Flow: "I expect [what]" • Why it matters: This becomes the KPI definition (Layer 3) and dashboard business narrative (Layer 4). Must be specific and measurable. • What enables: Signal definitions with targets (Layer 3), business health monitoring (Layer 4) • Good examples: - "credit checks to complete within 30 seconds during business hours" - "accurate credit scores returned for all requests (99.9% accuracy)" - "payment validation to process before appraisal scheduling deadlines" - "compliance pass rate of 95% or higher for all loan applications" • Avoid: "the service to work" (not measurable), "good performance" (undefined) • Pattern: [specific action] + [quality/timing constraint] + [scope/conditions] • Test: Is this measurable? Could you tell RIGHT NOW if it's being met? Can this become a signal with a target? • Domain knowledge: Banking/lending expectations often include timing (30 seconds, end-of-day cutoff), accuracy (99%+), compliance thresholds (regulatory requirements), and availability during business hours FIELD: Impact Description • Purpose: Complete the Semantic Flow: "If broken: [impact]" • Why it matters: Explains business consequence. This appears on dashboards and incident communications to answer "why should I care?" • What enables: Business impact quantification (Layer 3), priority/escalation decisions (Layer 4), executive communication (Layer 5) • Good examples: - "Loan applications are delayed, degrading customer experience and increasing risk of lost business to competitors" - "Risk assessments are inaccurate, creating compliance exposure and potential regulatory findings" - "Loan officers cannot submit applications, blocking daily pipeline progression and revenue targets" - "Regulatory reporting deadlines missed, triggering compliance escalation and potential penalties" • Avoid: "Bad things happen" (too vague), "Requests fail" (missing consequence) • Pattern: [immediate consequence] + [who is affected] + [business outcome at risk] • Test: Does this explain WHO suffers and WHAT business outcome is threatened? • Domain knowledge: Banking/lending impacts often cascade: customer experience → revenue loss → regulatory risk. Time-sensitive processes have hard deadlines (end-of-day, regulatory cutoffs). FIELD: Impact Category • Purpose: Classify the impact into one of four standard categories • Why it matters: Enables Layer 4 dashboards to show impact across all dimensions. Drives accountability for complete coverage. • What enables: 4-category dashboard display, executive impact visibility, prioritization frameworks • Categories: - Customer: Affects end-user experience, ability to achieve goals (apply for loan, complete transaction, receive decision) - Financial: Revenue loss, cost increase, penalties, dollars at risk, P&L impact - Legal/Risk: Compliance violations, regulatory exposure, audit findings, legal liability - Operational: Internal process failures, team productivity loss, SLA breaches, manual workaround burden • CRITICAL: Try to document expectations across ALL 4 categories for complete coverage. Even if "Not Defined" in some categories, documenting that drives accountability. • Test: Which business health dimension does this impact? • Domain knowledge: Financial services commonly hit all 4 categories: - Customer: Application delays, decision timeliness, user experience - Financial: Lost origination fees, increased costs, penalty risk - Legal/Risk: CFPB violations, fair lending compliance, audit exposure - Operational: Manual processing, team productivity, escalation burden FIELD: Priority • Purpose: Business criticality level for this expectation • Why it matters: Enables alert routing, escalation paths, and response prioritization • What enables: Critical path identification, executive escalation triggers, SLA definitions • Levels: - CRITICAL: Immediate business impact, executive notification required, revenue/compliance at risk - HIGH: Significant impact, same-day response required, stakeholder escalation likely - MEDIUM: Notable impact, address within normal workflow, monitor for escalation - LOW: Minor inconvenience, can be batched with other work, low urgency • Test: If this breaks at 2pm on Tuesday, what's the escalation timeline? • Domain knowledge: Financial services critical priorities often involve regulatory deadlines, customer-facing transactions during business hours, and compliance-sensitive processes --- SECTION 8: DOMAIN KNOWLEDGE - BANKING/LENDING PATTERNS ----------------------------------------------------- COMMON STAKEHOLDERS IN BANKING/LENDING: Customer Stakeholders: • Home buyers (mortgage applications) • Borrowers (loan management) • Account holders (banking services) • Applicants (credit decisioning) Internal Team Stakeholders: • Loan Officers (origination, customer interface) • Processors (application workflows, document validation) • Underwriters (risk assessment, approval decisions) • Compliance Analysts (regulatory validation, audit trails) • Operations Staff (exception handling, manual processes) • Credit Risk Team (risk models, portfolio management) • Treasury Team (funding, liquidity, settlements) Partner Stakeholders: • Mortgage Brokers (external origination) • Title Companies (closing coordination) • Appraisers (property valuation) • Credit Bureaus (credit data providers) Regulator Stakeholders: • CFPB (Consumer Financial Protection Bureau) • OCC (Office of Comptroller of Currency) • State Banking Authorities • Internal Audit Teams COMMON EXPECTATIONS IN BANKING/LENDING: Timing Expectations: • "within 30 seconds" (customer-facing decisioning) • "by end-of-day cutoff" (batch processing, regulatory reporting) • "within 2 business hours" (internal workflows) • "same-day processing" (operational commitments) Accuracy Expectations: • "99.9% accuracy for credit scores" • "zero tolerance for compliance validation errors" • "100% audit trail capture" • "field-level validation pass rate ≥ 99%" Availability Expectations: • "99.5% uptime during business hours (8am-6pm ET)" • "zero downtime during end-of-day processing window" • "24/7 availability for fraud detection" Compliance Expectations: • "95% compliance pass rate for loan applications" • "all regulatory reports submitted before deadline" • "audit trail complete for all transactions" COMMON IMPACTS IN BANKING/LENDING: Customer Impacts: • Application delays (missed rate locks, closing delays) • Decisioning delays (competitive disadvantage) • User experience degradation (frustration, abandonment) • Service unavailability (cannot complete transactions) Financial Impacts: • Lost origination fees ($2,000-$5,000 per loan) • Penalty risk (regulatory fines) • Increased operational costs (manual workarounds) • Revenue pipeline delays (quarterly targets at risk) Legal/Risk Impacts: • CFPB compliance violations • Fair lending exposure • Audit findings (internal/external) • Regulatory escalation required Operational Impacts: • Manual processing burden (hours per case) • Team productivity loss (blocked workflows) • Exception handling overhead • SLA breach escalations --- SECTION 9: HOW TO ASSIST PRODUCT OWNERS --------------------------------------- YOUR ASSISTANCE APPROACH: WHEN USER IS WORKING (Don't Overwhelm): • Provide tactical suggestions based on domain knowledge • Suggest stakeholders, expectations, impacts based on service type • Use patterns from Section 8 (banking/lending common patterns) • Keep explanations concise and action-oriented • Example: "Based on this being a Credit Check service in Home Lending, typical stakeholders might include Loan Officers (need fast decisions), Compliance Team (need audit trails), and Customers (need timely application progress)" WHEN USER ASKS "WHY?" (Explain Principles): • Connect to BOS architecture (Layers 1-5, Semantic Flow) • Explain which layer/principle this field enables • Show scale implications (n=1 vs n=5000) • Example: "Business Purpose is Layer 1 foundation - it enables requirements translation (Layer 2), signal definitions (Layer 3), and ultimately executive dashboards (Layer 5). At 5000 services, missing this context causes complete failure of downstream layers." SUGGESTION WORKFLOW: 1. Ask clarifying questions about service's business function 2. Propose 2-3 options based on domain knowledge (Section 8) 3. Explain why each option works for BOS 4. Let user choose or customize 5. Validate suggestion connects to Semantic Flow (Stakeholder → Expectation → Impact) IF USER DRAFT SEEMS TOO TECHNICAL: 1. Acknowledge what they wrote captures (don't dismiss) 2. Suggest business-focused alternative using domain knowledge 3. Explain: "This version will appear on dashboards and in incident communications - business stakeholders will read this" 4. Show the connection: "Technical → Business translation" IF USER IS STUCK ON IMPACT CATEGORIES: Walk through each category with specific question: • Customer: "Who outside your organization is affected when this fails? What can't they do?" • Financial: "What revenue is at risk? What costs increase? Are there penalties?" • Legal/Risk: "Are there compliance requirements? Regulatory exposure? Audit concerns?" • Operational: "Which internal teams are blocked? What manual workarounds are needed?" QUALITY CHECK BEFORE COMPLETION: - [ ] Service Name is business-recognizable (not technical jargon) - [ ] Business Purpose explains why business cares (not just what it does) - [ ] At least 3 stakeholder expectations documented (most services have 5-8) - [ ] Expectations are specific and measurable (could become signals with targets) - [ ] Impact descriptions explain business consequences (not just "it's broken") - [ ] Multiple impact categories represented (ideally all 4 - drives accountability) - [ ] Priorities reflect actual business criticality (escalation paths clear) - [ ] Semantic Flow is complete: Each row has Stakeholder → Expectation → Impact REMEMBER: • You have comprehensive BOS principles context (Sections 1-5) • User needs tactical assistance without theory dump • Explain principles WHEN ASKED, suggest tactically OTHERWISE • Connect tactical work to strategic architecture when helpful • Use domain knowledge (Section 8) for contextually appropriate suggestions • Your role: Make Product Owner successful at building Layer 1 foundation ========================================== END COPILOT CONTEXT ========================================== ```

Sheet Instructions
A1: NOTE: Key instructions are now integrated into the Service Entry Form and Stakeholder Expectations tabs. This tab provides complete reference documentation. --- # BOS Onboarding Workbook v1.0 - Instructions ## Purpose This workbook captures essential information about your service for the Business Observability System (BOS). The information you provide becomes the foundation for monitoring your service's business health and impact. **What you'll create:** - Clear understanding of your service's business value - Documentation of stakeholder expectations - Foundation for business observability dashboards and alerts **What happens with this data:** Your entries will be imported into BOS and used to generate: - Service-level dashboards showing business health in real-time - Stakeholder-focused views of expectations and impacts - Automated alerts when business expectations are at risk - Executive rollups showing business health across all services --- ## How to Use This Workbook ### Step 1: Service Metadata Tab 1. Navigate to the "Service Metadata" tab 2. Fill out one row with your service's basic information: - **Service Name**: What you call this service (used throughout BOS) - **Business Purpose**: What business problem this service solves (focus on value, not technology) - **L4 Product Line / L3 Product**: Your service's organizational placement - **Product Owner**: Your email address - **CMDB Application ID**: Optional - if you know your CMDB ID, include it ### Step 2: Business Context Tab 1. Navigate to the "Business Context" tab 2. Add one row for each stakeholder expectation (typically 3-8 per service) 3. Think through: Who depends on this service? What do they expect? 4. Use the pattern: "As a [stakeholder], I expect [what]. If broken: [impact]" ### Step 3: Save and Share - Save your work frequently (workbook can be online/SharePoint for collaboration) - You can complete this over multiple sessions - no need to finish in one sitting - When complete, share with the BOS team for import --- ## Time Required **Estimated:** 1-2 hours total **Can be paused:** Yes! Save your work and return later. The workbook supports: - Individual completion (Product Owner fills out alone) - Collaborative completion (share file, work with team members) - Iterative refinement (start with basics, add detail over time) --- ## Field Guidance Quick Reference ### Service Metadata Tab Fields **Service Name** - What do you call this service? - Use business-recognizable names (not technical infrastructure terms) - This name appears on dashboards, alerts, and reports - Example: "Credit Check Service" (good) vs "API Gateway Cluster 3" (avoid) **Business Purpose** - What business problem does this service solve? - Focus on business value, not technical implementation - Explain WHY this service exists from a business perspective - Example: "Enables home loan applicants to receive credit decisions within 30 seconds during business hours to support lending operations" **L4 Product Line / L3 Product** - Your organizational placement - Select your service's L4 Product Line (highest level organizational unit) - Select your L3 Product (specific product within that line) - If unsure, check with your manager or CMDB records **Product Owner** - Who owns this service's business outcomes? - Use email address for traceability - This person is the authoritative source for business context - This person validates expectations and business impact definitions **CMDB Application ID** - Optional connection to existing systems - If your service has a CMDB Application ID, include it here - Helps connect BOS to existing configuration management - Leave blank if unknown - not required for BOS to work ### Business Context Tab Fields **Stakeholder Type** - Who is this stakeholder? - Common types: Customer, Internal Team, Partner, Regulator, Executive - Think: Who would call/complain if this service fails? **Specific Group** - Which specific group within this stakeholder type? - Be specific enough to notify the right people during incidents - Example: "Home Lending Processors", "Credit Risk Team", "Compliance Analysts" - Test: Can you identify this group's manager or send them an email? **Expectation Statement** - Complete: "As this stakeholder, I expect..." - Be specific and measurable - Include timing, accuracy, or performance expectations - Examples: - "credit checks to complete within 30 seconds during business hours" - "accurate credit scores returned for all requests (99.9% accuracy)" - "audit trail complete for all transactions with timestamps" **Impact Description** - What happens if this expectation is not met? - Explain business consequences (not just "it's broken") - Who is affected? What business outcome is threatened? - Examples: - "loan applications are delayed, customer experience degraded, risk of losing business to competitors" - "risk assessments are inaccurate, potential revenue loss from bad credit decisions" - "regulatory findings possible, compliance escalation required" **Impact Category** - What type of impact? - **Customer**: Affects end-user experience or ability to achieve goals - **Financial**: Revenue loss, cost increase, penalties, dollars at risk - **Legal/Risk**: Compliance violations, regulatory exposure, audit findings - **Operational**: Internal process failures, team productivity loss, manual workarounds **Priority** - How critical is this expectation? - **CRITICAL**: Immediate business impact, executive notification, revenue/compliance at risk - **HIGH**: Significant impact, same-day response required, stakeholder escalation likely - **MEDIUM**: Notable impact, address within normal workflow, monitor for escalation - **LOW**: Minor inconvenience, can be batched with other work, low urgency --- ## Common Patterns: The User Story Format BOS uses a user story pattern that appears throughout the system: **Pattern:** "As a [Stakeholder Type: Specific Group], I expect [Expectation Statement]. If broken: [Impact Description] ([Impact Category], [Priority])" **Example:** "As a Customer: Home Lending Processors, I expect credit checks to complete within 30 seconds during business hours. If broken: loan applications are delayed, customer experience degraded, risk of losing business to competitors (Customer, CRITICAL)" **Why this pattern:** - Connects technical signals to business stakeholders - Makes business impact explicit - Drives prioritization based on who is affected - Appears on dashboards exactly as you write it --- ## Four Impact Categories: Drive Complete Coverage Try to document expectations across ALL four impact categories: 1. **Customer** - End-user experience and goal achievement 2. **Financial** - Revenue, costs, penalties, P&L impact 3. **Legal/Risk** - Compliance, regulations, audit exposure 4. **Operational** - Internal processes, team productivity, manual burden **Why this matters:** - Financial services commonly hit all 4 categories - Even if "not defined" in some categories, documenting that drives accountability - Complete coverage ensures executive visibility into all business health dimensions - Helps prioritize response during incidents (Customer + Financial + Legal = highest priority) --- ## What Happens Next: Your Data Becomes BOS Operational Data **Production Data Path:** 1. **You complete this workbook** - Capture service metadata and stakeholder expectations 2. **BOS team imports your data** - Direct import to BOS database (no migration pain) 3. **Dashboards generate automatically** - Your expectations become dashboard panels 4. **Alerts configure automatically** - Your priorities drive escalation paths 5. **Business health visible immediately** - Stakeholders see real-time status **This is not a planning exercise** - This data becomes THE operational system. **Your words appear verbatim:** - Service Name: Appears on all dashboards and alerts - Business Purpose: Appears on service detail pages - Expectation Statements: Appear on dashboards as-is - Impact Descriptions: Appear in incident communications **Write for your audience:** - Executives will read this during escalations - Operations teams will use this to understand priorities - Other Product Owners will reference this for patterns - Future teams will rely on this when you're not available --- ## Need Help? **Questions about:** - BOS concepts or methodology - How to describe your service's business value - Which stakeholders to document - How to measure expectations **Contact:** BOS team [contact information will be provided] **Resources:** - BOS principles documentation - Example services for reference - Stakeholder discovery workshops available --- ## Workbook Structure Reference **Tab 1: Dashboard Mockup** - Preview how your data will appear on BOS dashboards **Tab 2: Copilot** - AI assistant context (use Microsoft Copilot for help completing this workbook) **Tab 3: Instructions** - This tab (guidance for Product Owners) **Tab 4: Service Metadata** - Step 1: Your service's basic information (1 row) **Tab 5: Business Context** - Step 2: Stakeholder expectations (3-8 rows typically) --- **Version:** 1.0 (Steps 1-2: Service + Business Context) **Scope:** This version captures foundational business context. Future versions will extend to signal definitions and technical implementation details.
A3: PURPOSE
A4: This workbook captures essential information about your service for Business Observability System (BOS).
A6: WHAT YOU'LL PROVIDE
A7: 1. Service Metadata - Basic identification and ownership
A8: 2. Business Context - Stakeholder expectations and impacts
A10: TIME REQUIRED
A11: 1-2 hours (can be completed in multiple sessions)
A13: HOW TO USE THIS WORKBOOK
A14: 1. Start with 'Service Metadata' tab - fill out one row for your service
A15: 2. Move to 'Business Context' tab - add one row per stakeholder expectation
A16: 3. Save and share when complete (file can be online/SharePoint for collaboration)
... A25: Contact the BOS team for assistance with any fields or concepts.

Sheet Service Entry Form
A1: BOS ONBOARDING - SERVICE METADATA
A3: Step 1: Define Your Service - Complete the fields below. Required fields marked with *
A5: SERVICE INFORMATION
A6: Field | B6: Your Answer | C6: Helper Text
A7: L4 Product Line / L3 Product * | B7: Home Lending → Home Originations | C7: Required
A8: Which product line and product does this service belong to? This helps organize services by business unit.
A9: CMDB Application ID * | B9: CORE_HOME_ORIG | C9: Required
A10: Primary CMDB Application ID for this service (e.g., CORE_HOME_ORIG). Required as of v3.7.
A11: Service Name * | B11: Credit Check Service | C11: Required
A12: What do you call this service? This name will be used throughout BOS dashboards and alerts.
A13: Business Purpose * | B13: Enables home loan applicants to receive credit decisions within 30 seconds during business hours to support lending operations | C13: Required
A14: What business problem does this service solve? Focus on business value, not technical implementation.
A15: Product Owner * | B15: jane.smith@company.com | C15: Required
A16: Who is the product owner? Email address recommended for traceability.
A18: After completing, proceed to 'Stakeholder Expectations' tab to document business context.

Sheet Stakeholder Expectations
A1: BOS ONBOARDING - STAKEHOLDER EXPECTATIONS
A3: Step 2: Document Expectations - Add 3-8 expectations (one per section below). Use pattern: "As [who], I expect [what]. If broken: [impact]"
A5: EXPECTATION #1
A6: Stakeholder * | B6: Home Lending Processors | C6: Required
A7: Who depends on this service? Describe in your own terms. (e.g., Mortgage Applicants, Credit Risk Team)
A8: Expectation Statement * | B8: credit checks to complete within 30 seconds during business hours | C8: Required
A9: Complete: "As this stakeholder, I expect..." Be specific and measurable.
A10: Impact Description * | B10: loan applications are delayed, customer experience degraded, risk of losing business to competitors | C10: Required
A11: What happens if this expectation is not met? Explain business consequences.
A12: Impact Category * | B12: Customer | C12: Required
A13: Priority * | B13: CRITICAL | C13: Required
A15: EXPECTATION #2
A16: Stakeholder * | B16: Credit Risk Team | C16: Required
A17: Who depends on this service? Describe in your own terms. (e.g., Mortgage Applicants, Credit Risk Team)
A18: Expectation Statement * | B18: accurate credit scores returned for all requests (99.9% accuracy) | C18: Required
A19: Complete: "As this stakeholder, I expect..." Be specific and measurable.
A20: Impact Description * | B20: risk assessments are inaccurate, potential revenue loss from bad credit decisions, portfolio risk exposure | C20: Required
A21: What happens if this expectation is not met? Explain business consequences.
A22: Impact Category * | B22: Financial | C22: Required
A23: Priority * | B23: HIGH | C23: Required
A25: EXPECTATION #3
A26: Stakeholder * | B26: Compliance Team | C26: Required
A27: Who depends on this service? Describe in your own terms. (e.g., Mortgage Applicants, Credit Risk Team)
A28: Expectation Statement * | B28: audit trail complete for all transactions with timestamps and decision rationale | C28: Required
A29: Complete: "As this stakeholder, I expect..." Be specific and measurable.
A30: Impact Description * | B30: regulatory findings possible, compliance escalation required, potential CFPB violations | C30: Required
A31: What happens if this expectation is not met? Explain business consequences.
A32: Impact Category * | B32: Legal/Risk | C32: Required
A33: Priority * | B33: CRITICAL | C33: Required
A35: EXPECTATION #4
A36: Stakeholder * | B36: Operations Staff | C36: Required
A37: Who depends on this service? Describe in your own terms. (e.g., Mortgage Applicants, Credit Risk Team)
A38: Expectation Statement * | B38: exception handling workload remains manageable (< 5% manual intervention rate) | C38: Required
A39: Complete: "As this stakeholder, I expect..." Be specific and measurable.
A40: Impact Description * | B40: team productivity loss, manual processing burden increases, overtime costs escalate | C40: Required
A41: What happens if this expectation is not met? Explain business consequences.
A42: Impact Category * | B42: Operational | C42: Required
A43: Priority * | B43: MEDIUM | C43: Required
